pretty_help/__init__.py
pretty_help/menu.py
pretty_help/pretty_help.py
nextcord_pretty_help-1.3.3.dist-info/entry_points.txt
nextcord_pretty_help-1.3.3.dist-info/LICENSE
nextcord_pretty_help-1.3.3.dist-info/WHEEL
nextcord_pretty_help-1.3.3.dist-info/METADATA
nextcord_pretty_help-1.3.3.dist-info/RECORD
