Metadata-Version: 2.1
Name: nextcord-pretty-help
Version: 1.3.3
Summary: An embed-based version of the built in help command for Nextcord
Home-page: https://github.com/squigjess/nextcord-pretty-help
License: MIT
Keywords: discord,nextcord,discord bot
Author: squigjess
Author-email: 701075+squigjess@users.noreply.github.com
Requires-Python: >=3.9,<4.0
Classifier: License :: OSI Approved :: MIT License
Classifier: Programming Language :: Python :: 3
Classifier: Programming Language :: Python :: 3.10
Classifier: Programming Language :: Python :: 3.9
Project-URL: Repository, https://github.com/squigjess/nextcord-pretty-help
